inventree_brother/__init__.py
inventree_brother/brother_plugin.py
inventree_brother_plugin-2.0.5.dist-info/licenses/LICENSE
inventree_brother_plugin-2.0.5.dist-info/METADATA
inventree_brother_plugin-2.0.5.dist-info/WHEEL
inventree_brother_plugin-2.0.5.dist-info/entry_points.txt
inventree_brother_plugin-2.0.5.dist-info/top_level.txt
inventree_brother_plugin-2.0.5.dist-info/RECORD
