Metadata-Version: 2.4
Name: inventree-brother-plugin
Version: 2.0.5
Summary: Brother label printer plugin for InvenTree
Home-page: https://github.com/inventree/inventree-brother-plugin
Author: Oliver Walters
Author-email: oliver.henry.walters@gmail.com
License: MIT
Keywords: inventree label printer printing inventory
Classifier: Programming Language :: Python :: 3
Classifier: Operating System :: OS Independent
Classifier: Framework :: InvenTree
Requires-Python: >=3.9
License-File: LICENSE
Requires-Dist: brother-ql-inventree>=1.1
Dynamic: author
Dynamic: author-email
Dynamic: classifier
Dynamic: description
Dynamic: description-content-type
Dynamic: home-page
Dynamic: keywords
Dynamic: license
Dynamic: license-file
Dynamic: requires-dist
Dynamic: requires-python
Dynamic: summary
